rule34_posts_wrapper/__init__.py
rule34_posts_wrapper/__version__.py
rule34_posts_wrapper/posts_wrapper.py
rule34_posts_wrapper/tags_wrapper.py
rule34_posts_wrapper/utils.py
rule34_posts_wrapper/objects/__init__.py
rule34_posts_wrapper/objects/page.py
rule34_posts_wrapper/objects/post.py
rule34_posts_wrapper/objects/tag.py
Rule34_Posts_Wrapper-0.1.1.1.dist-info/LICENSE
Rule34_Posts_Wrapper-0.1.1.1.dist-info/METADATA
Rule34_Posts_Wrapper-0.1.1.1.dist-info/WHEEL
Rule34_Posts_Wrapper-0.1.1.1.dist-info/top_level.txt
Rule34_Posts_Wrapper-0.1.1.1.dist-info/RECORD
