Metadata-Version: 2.1
Name: Rule34-Posts-Wrapper
Version: 0.1.1.1
Summary: Library for retrieving posts and tags from rule34.paheal.net
Home-page: https://github.com/nukdokplex/rule34-posts-wrapper
Author: NukDokPlex
Author-email: nukdokpelx@outlook.com
License: MIT
Classifier: Development Status :: 3 - Alpha
Classifier: Topic :: Multimedia
Classifier: Topic :: Games/Entertainment
Classifier: Topic :: Internet
Classifier: Topic :: Internet :: WWW/HTTP
Classifier: Topic :: Internet :: WWW/HTTP :: Indexing/Search
Classifier: Programming Language :: Python :: 3.10
Classifier: Programming Language :: Python :: 3
Classifier: License :: OSI Approved :: MIT License
Classifier: Operating System :: OS Independent
License-File: LICENSE
Requires-Dist: requests
Requires-Dist: lxml
Requires-Dist: beautifulsoup4
Requires-Dist: soupsieve
Requires-Dist: urllib3
Provides-Extra: development
Requires-Dist: coverage ; extra == 'development'
Requires-Dist: pytest ; extra == 'development'
Requires-Dist: pytest-cov ; extra == 'development'
Requires-Dist: pre-commit ; extra == 'development'
Requires-Dist: tox ; extra == 'development'
